mri_pop_vis/GroupStatistics.py
mri_pop_vis/Preprocessing.py
mri_pop_vis/__init__.py
mri_pop_vis/main_app.py
mri_pop_vis/mri_pop_vis.py
mri_pop_vis/table_create.py
mri_pop_vis/zscores.py
mri_pop_vis-0.1.0.dist-info/METADATA
mri_pop_vis-0.1.0.dist-info/RECORD
mri_pop_vis-0.1.0.dist-info/WHEEL
mri_pop_vis-0.1.0.dist-info/top_level.txt
