Metadata-Version: 2.1
Name: mri-pop-vis
Version: 0.1.0
Summary: Python Boilerplate contains all the boilerplate you need to create a Python package.
Home-page: https://github.com/amygreen/Pyhack
Author: Ayam Greental, Hila Gast, Omri Tomer, Gadi Drori, Shira Halabi
Author-email: ayam.greental@gmail.com
License: MIT license
Keywords: mri_pop_vis
Platform: UNKNOWN
Classifier: Development Status :: 2 - Pre-Alpha
Classifier: Intended Audience :: Developers
Classifier: License :: OSI Approved :: MIT License
Classifier: Natural Language :: English
Classifier: Programming Language :: Python :: 3.6
